pylivecoinwatch/__init__.py
pylivecoinwatch/api.py
tests/__init__.py
tests/test_api.py
pylivecoinwatch-1.2.3.dist-info/LICENSE
pylivecoinwatch-1.2.3.dist-info/METADATA
pylivecoinwatch-1.2.3.dist-info/WHEEL
pylivecoinwatch-1.2.3.dist-info/top_level.txt
pylivecoinwatch-1.2.3.dist-info/RECORD
