Metadata-Version: 2.1
Name: pylivecoinwatch
Version: 1.2.3
Summary: Python wrapper around Live Coin Watch API
Home-page: https://github.com/PlayErphil/LCW-API-Wrapper
Author: Rene Gonzalez
License: MIT
Keywords: crypto,crypto bot,livecoinwatch
Classifier: Programming Language :: Python :: 3
Classifier: Programming Language :: Python :: 2
Classifier: License :: OSI Approved :: MIT License
Classifier: Operating System :: OS Independent
License-File: LICENSE
Requires-Dist: requests
